[
  {
    "businessTypeCode":"05",
    "businessTypeName":"Alaskan Native Corporation Owned Firm"
  },
  {
    "businessTypeCode":"12",
    "businessTypeName":"U.S. Local Government"
  },
  {
    "businessTypeCode":"1A",
    "businessTypeName":"Minority Institution"
  },
  {
    "businessTypeCode":"1B",
    "businessTypeName":"Tribally Owned Firm"
  },
  {
    "businessTypeCode":"1D",
    "businessTypeName":"Small Agricultural Cooperative"
  },
  {
    "businessTypeCode":"1R",
    "businessTypeName":"Private University or College"
  },
  {
    "businessTypeCode":"20",
    "businessTypeName":"Foreign Owned and Located"
  },
  {
    "businessTypeCode":"23",
    "businessTypeName":"Minority Owned Business"
  },
  {
    "businessTypeCode":"27",
    "businessTypeName":"Self Certified Small Disadvantaged Business"
  },
  {
    "businessTypeCode":"2A",
    "businessTypeName":"U.S. Government Entity"
  },
  {
    "businessTypeCode":"2F",
    "businessTypeName":"U.S. State Government"
  },
  {
    "businessTypeCode":"2J",
    "businessTypeName":"Sole Proprietorship "
  },
  {
    "businessTypeCode":"2K",
    "businessTypeName":"Partnership or Limited Liability Partnership"
  },
  {
    "businessTypeCode":"2L",
    "businessTypeName":"Corporate Entity (Not Tax Exempt)"
  },
  {
    "businessTypeCode":"2R",
    "businessTypeName":"U.S Federal Government"
  },
  {
    "businessTypeCode":"2R",
    "businessTypeName":"US Federal Government"
  },
  {
    "businessTypeCode":"2U",
    "businessTypeName":"Other Not For Profit Organization"
  },
  {
    "businessTypeCode":"2X",
    "businessTypeName":"For Profit Organization"
  },
  {
    "businessTypeCode":"3I",
    "businessTypeName":"Tribal Government"
  },
  {
    "businessTypeCode":"6D",
    "businessTypeName":"Domestic Shelter"
  },
  {
    "businessTypeCode":"80",
    "businessTypeName":"Hospital"
  },
  {
    "businessTypeCode":"86",
    "businessTypeName":"Interstate Entity"
  },
  {
    "businessTypeCode":"8B",
    "businessTypeName":"Housing Authorities Public/Tribal"
  },
  {
    "businessTypeCode":"8C",
    "businessTypeName":"Joint Venture Women Owned Small Business"
  },
  {
    "businessTypeCode":"8D",
    "businessTypeName":"Joint Venture Economically Disadvantaged Women Small Owned Business"
  },
  {
    "businessTypeCode":"8E",
    "businessTypeName":"Economically Disadvantaged Women Small Owned Business"
  },
  {
    "businessTypeCode":"8H",
    "businessTypeName":"Corporate Entity (Tax Exempt)"
  },
  {
    "businessTypeCode":"8U",
    "businessTypeName":"Native Hawaiian Organization Owned Firm"
  },
  {
    "businessTypeCode":"8W",
    "businessTypeName":"Woman Owned Small Business"
  },
  {
    "businessTypeCode":"A2",
    "businessTypeName":"Woman Owned Business"
  },
  {
    "businessTypeCode":"A3",
    "businessTypeName":"Labor Surplus Area Firm"
  },
  {
    "businessTypeCode":"A4",
    "businessTypeName":"SBA Certified Small Disadvantaged Business "
  },
  {
    "businessTypeCode":"A5",
    "businessTypeName":"Veteran Owned Business"
  },
  {
    "businessTypeCode":"A6",
    "businessTypeName":"SBA Certified 8(a) Program Participant "
  },
  {
    "businessTypeCode":"A7",
    "businessTypeName":"AbilityOne Non Profit Agency"
  },
  {
    "businessTypeCode":"A8",
    "businessTypeName":"Non-Profit Organization"
  },
  {
    "businessTypeCode":"BZ",
    "businessTypeName":"Foundation"
  },
  {
    "businessTypeCode":"C6",
    "businessTypeName":"Municipality"
  },
  {
    "businessTypeCode":"C7",
    "businessTypeName":"County"
  },
  {
    "businessTypeCode":"C8",
    "businessTypeName":"City"
  },
  {
    "businessTypeCode":"CY",
    "businessTypeName":"Country - Foreign Government"
  },
  {
    "businessTypeCode":"F",
    "businessTypeName":"Business or Organization"
  },
  {
    "businessTypeCode":"FO",
    "businessTypeName":"Township"
  },
  {
    "businessTypeCode":"FR",
    "businessTypeName":"Asian-Pacific American Owned"
  },
  {
    "businessTypeCode":"FY",
    "businessTypeName":"Veterinary Hospital"
  },
  {
    "businessTypeCode":"G3",
    "businessTypeName":"Alaskan Native Servicing Institution"
  },
  {
    "businessTypeCode":"G5",
    "businessTypeName":"Native Hawaiian Servicing Institution"
  },
  {
    "businessTypeCode":"G6",
    "businessTypeName":"1862 Land Grant College"
  },
  {
    "businessTypeCode":"G7",
    "businessTypeName":"1890 Land Grant College"
  },
  {
    "businessTypeCode":"G8",
    "businessTypeName":"1994 Land Grant College"
  },
  {
    "businessTypeCode":"G9",
    "businessTypeName":"Other Than One of the Proceeding"
  },
  {
    "businessTypeCode":"GW",
    "businessTypeName":"Hispanic Servicing Institution"
  },
  {
    "businessTypeCode":"H2",
    "businessTypeName":"Community Development Corporation "
  },
  {
    "businessTypeCode":"H6",
    "businessTypeName":"School District"
  },
  {
    "businessTypeCode":"HB",
    "businessTypeName":"Historically Black College or University"
  },
  {
    "businessTypeCode":"HK",
    "businessTypeName":"Community Development Corporation Owned Firm"
  },
  {
    "businessTypeCode":"HQ",
    "businessTypeName":"DOT Certified DBE"
  },
  {
    "businessTypeCode":"HS",
    "businessTypeName":"Tribal College"
  },
  {
    "businessTypeCode":"JT",
    "businessTypeName":"SBA Certified 8(a) Joint Venture"
  },
  {
    "businessTypeCode":"KM",
    "businessTypeName":"Planning Commission"
  },
  {
    "businessTypeCode":"LJ",
    "businessTypeName":"Limited Liability Company"
  },
  {
    "businessTypeCode":"M8",
    "businessTypeName":"Educational Institution"
  },
  {
    "businessTypeCode":"MF",
    "businessTypeName":"Manufacturer of Goods"
  },
  {
    "businessTypeCode":"MG",
    "businessTypeName":"Local Government Owned"
  },
  {
    "businessTypeCode":"NB",
    "businessTypeName":"Native American Owned"
  },
  {
    "businessTypeCode":"NG",
    "businessTypeName":"Federal Agency"
  },
  {
    "businessTypeCode":"OH",
    "businessTypeName":"State Controlled Institution of Higher Learning"
  },
  {
    "businessTypeCode":"OW",
    "businessTypeName":"American Indian Owned"
  },
  {
    "businessTypeCode":"OY",
    "businessTypeName":"Black American Owned"
  },
  {
    "businessTypeCode":"PI",
    "businessTypeName":"Hispanic American Owned"
  },
  {
    "businessTypeCode":"QF",
    "businessTypeName":"Service Disabled Veteran Owned Business"
  },
  {
    "businessTypeCode":"QU",
    "businessTypeName":"Veterinary College"
  },
  {
    "businessTypeCode":"QW",
    "businessTypeName":"Federally Funded Research and Development Corp"
  },
  {
    "businessTypeCode":"QZ",
    "businessTypeName":"Subcontinent Asian (Asian-Indian) American Owned"
  },
  {
    "businessTypeCode":"S4",
    "businessTypeName":"Buyer"
  },
  {
    "businessTypeCode":"S5",
    "businessTypeName":"Seller"
  },
  {
    "businessTypeCode":"S6",
    "businessTypeName":"Buyer & Seller"
  },
  {
    "businessTypeCode":"T4",
    "businessTypeName":"Port Authority"
  },
  {
    "businessTypeCode":"TR",
    "businessTypeName":"Airport Authority"
  },
  {
    "businessTypeCode":"TW",
    "businessTypeName":"Transit Authority"
  },
  {
    "businessTypeCode":"UD",
    "businessTypeName":"Council of Governments"
  },
  {
    "businessTypeCode":"X6",
    "businessTypeName":"International Organization"
  },
  {
    "businessTypeCode":"XS",
    "businessTypeName":"Subchapter S Corporation"
  },
  {
    "businessTypeCode":"XX",
    "businessTypeName":"SBA Certified Hub Zone Firm "
  },
  {
    "businessTypeCode":"XY",
    "businessTypeName":"Indian Tribe (Federally Recognized)"
  },
  {
    "businessTypeCode":"Z1",
    "businessTypeName":"Federal Assistance Awards"
  },
  {
    "businessTypeCode":"Z2",
    "businessTypeName":"All Awards"
  },
  {
    "businessTypeCode":"Z3",
    "businessTypeName":"IGT Only"
  },
  {
    "businessTypeCode":"Z4",
    "businessTypeName":"Assistance Awards & IGT"
  },
  {
    "businessTypeCode":"Z5",
    "businessTypeName":"All Awards and IGT"
  },
  {
    "businessTypeCode":"ZR",
    "businessTypeName":"Inter-municipal"
  },
  {
    "businessTypeCode":"ZW",
    "businessTypeName":"School of Forestry"
  },
  {
    "businessTypeCode":"ZZ",
    "businessTypeName":"Other"
  }
]
